[
    {
        "id": "honda",
        "sample1_1": 4.464274,
        "sample1_2": 7.087345,
        "sample2_1": 2.659297,
        "sample2_2": 83.5136,
        "sample2_3": 49.299961,
        "sample3_1": 22.99157,
        "sample3_2": 19.679316
    },
    {
        "id": "audi",
        "sample1_1": 1.454645,
        "sample1_2": 2.784645,
        "sample2_1": 2.692656,
        "sample2_2": 14.01095,
        "sample2_3": 7.674361,
        "sample3_1": 3.84253,
        "sample3_2": 3.795233
    }
]